apigateway/__init__.py
apigateway/clients/__init__.py
apigateway/clients/client.py
apigateway/clients/constants.py
apigateway/exceptions/__init__.py
apigateway/exceptions/exceptions.py
apigateway/models/__init__.py
apigateway/models/consumer.py
apigateway/models/plugin_config.py
apigateway/models/route.py
apigateway/models/upstream.py
apigateway/models/upstream_host.py
apigatewaysdk-0.2.dist-info/LICENSE.txt
apigatewaysdk-0.2.dist-info/METADATA
apigatewaysdk-0.2.dist-info/WHEEL
apigatewaysdk-0.2.dist-info/top_level.txt
apigatewaysdk-0.2.dist-info/RECORD
